asva/Analysis.py
asva/Damper.py
asva/Exporter.py
asva/Loader.py
asva/Model.py
asva/Plot.py
asva/Response.py
asva/Types.py
asva/__init__.py
asva/dampers/Damper.py
asva/dampers/MASS.py
asva/dampers/Stopper.py
asva/dampers/TMD.py
asva/dampers/VDA.py
asva/dampers/VDB.py
asva/dampers/__init__.py
asva/dampers/iRDT.py
asva/restoring_force/Bilinear.py
asva/restoring_force/Elastic.py
asva/restoring_force/Gyakko.py
asva/restoring_force/RestoringForce.py
asva/restoring_force/Takeda.py
asva/restoring_force/Trilinear.py
asva/restoring_force/__init__.py
asva/src/Analysis.py
asva/src/Damper.py
asva/src/Model.py
asva/src/Plot.py
asva/src/Response.py
asva/src/Types.py
asva/src/__init__.py
asva/src/dampers/Damper.py
asva/src/dampers/MASS.py
asva/src/dampers/Stopper.py
asva/src/dampers/TMD.py
asva/src/dampers/VDA.py
asva/src/dampers/VDB.py
asva/src/dampers/__init__.py
asva/src/dampers/iRDT.py
asva/src/restoring_force/Bilinear.py
asva/src/restoring_force/Elastic.py
asva/src/restoring_force/Gyakko.py
asva/src/restoring_force/RestoringForce.py
asva/src/restoring_force/Takeda.py
asva/src/restoring_force/Trilinear.py
asva/src/restoring_force/__init__.py
asva/src/utils/__init__.py
asva/src/utils/calculations.py
asva/src/utils/colors.py
asva/src/utils/config.py
asva/src/utils/damper.py
asva/src/utils/delta.py
asva/src/utils/normalize.py
asva/src/utils/shear_force.py
asva/src/utils/str_list.py
asva/src/utils/time_step.py
asva/src/utils/wave.py
asva/utils/__init__.py
asva/utils/calculations.py
asva/utils/colors.py
asva/utils/config.py
asva/utils/damper.py
asva/utils/delta.py
asva/utils/normalize.py
asva/utils/shear_force.py
asva/utils/str_list.py
asva/utils/time_step.py
asva/utils/wave.py
examples/__init__.py
examples/basic.py
examples/configs.py
examples/minimum.py
asva-0.3.1.dist-info/LICENSE.md
asva-0.3.1.dist-info/METADATA
asva-0.3.1.dist-info/WHEEL
asva-0.3.1.dist-info/top_level.txt
asva-0.3.1.dist-info/RECORD
