Metadata-Version: 2.1
Name: asva
Version: 0.3.1
Summary: Vibration analysis program for multi degree of freedom model
Home-page: https://github.com/adc21/asva
Author: adc21
Author-email: aseismic.device@gmail.com
Maintainer: adc21
Maintainer-email: aseismic.device@gmail.com
License: MIT
Platform: UNKNOWN
Classifier: Programming Language :: Python :: 3.8
Classifier: License :: OSI Approved :: MIT License
Requires-Python: >=3.8
Requires-Dist: matplotlib (==3.2.1)
Requires-Dist: numpy (==1.18.4)
Requires-Dist: pandas (==1.0.3)
Requires-Dist: tqdm (==4.46.1)
